{"key":"4M3","name":"Carlisle Municipal Airport","city":"Carlisle","state":"AR","lat":34.808201,"lon":-91.712097,"elev":241,"runways":[{"id":"09/27","lengthFt":4501,"widthFt":75,"surfaceCode":"ASP","lowEnd":{"id":"09","heading":91.1,"lat":34.80599976,"lon":-91.72250366,"displacedThresholdFt":0},"highEnd":{"id":"27","heading":271.1,"lat":34.80580139,"lon":-91.70749664,"displacedThresholdFt":0}},{"id":"18/36","lengthFt":4494,"widthFt":75,"surfaceCode":"ASP","lowEnd":{"id":"18","heading":181.1,"lat":34.81669998,"lon":-91.70899963,"displacedThresholdFt":0},"highEnd":{"id":"36","heading":1.1,"lat":34.8042984,"lon":-91.709198,"displacedThresholdFt":0}}]}
