{"key":"B16","name":"Whitfords Airport","city":"Weedsport","state":"NY","lat":43.080299,"lon":-76.538399,"elev":400,"runways":[{"id":"10L/28R","lengthFt":3630,"widthFt":60,"surfaceCode":"ASP","lowEnd":{"id":"10L","heading":86.9,"lat":43.080501556396484,"lon":-76.54609680175781,"displacedThresholdFt":430},"highEnd":{"id":"28R","heading":266.9,"lat":43.08100128173828,"lon":-76.53250122070312,"displacedThresholdFt":350}},{"id":"10R/28L","lengthFt":2800,"widthFt":100,"surfaceCode":"GRS","lowEnd":{"id":"10R","heading":88,"lat":43.079498291015625,"lon":-76.54239654541016,"displacedThresholdFt":0},"highEnd":{"id":"28L","heading":268,"lat":43.07979965209961,"lon":-76.53189849853516,"displacedThresholdFt":0}}]}
