{"key":"D55","name":"Robertson Field","city":"Langdon","state":"ND","lat":48.752998,"lon":-98.393303,"elev":1608,"runways":[{"id":"08/26","lengthFt":1930,"widthFt":100,"surfaceCode":"GRS","lowEnd":{"id":"08","heading":90,"lat":48.75640106,"lon":-98.39420319,"displacedThresholdFt":0},"highEnd":{"id":"26","heading":270,"lat":48.75640106,"lon":-98.38439941,"displacedThresholdFt":0}},{"id":"14/32","lengthFt":3600,"widthFt":60,"surfaceCode":"ASP","lowEnd":{"id":"14","heading":140.1,"lat":48.7588996887207,"lon":-98.39749908447266,"displacedThresholdFt":0},"highEnd":{"id":"32","heading":320.1,"lat":48.751399993896484,"lon":-98.38809967041016,"displacedThresholdFt":0}}]}
