{"key":"KCAR","icao":"KCAR","name":"Caribou Municipal Airport","city":"Caribou","state":"ME","lat":46.871498,"lon":-68.017899,"elev":626,"runways":[{"id":"01/19","lengthFt":4003,"widthFt":100,"surfaceCode":"ASP","lowEnd":{"id":"01","heading":347.3,"lat":46.86819839477539,"lon":-68.01490020751953,"displacedThresholdFt":0},"highEnd":{"id":"19","heading":167.3,"lat":46.87889862060547,"lon":-68.01850128173828,"displacedThresholdFt":0}},{"id":"11/29","lengthFt":3016,"widthFt":75,"surfaceCode":"ASP","lowEnd":{"id":"11","heading":86,"lat":46.86880112,"lon":-68.02619934,"displacedThresholdFt":0},"highEnd":{"id":"29","heading":266,"lat":46.86920166,"lon":-68.01409912,"displacedThresholdFt":0}}]}
