{"key":"KCDR","icao":"KCDR","name":"Chadron Municipal Airport","city":"Chadron","state":"NE","lat":42.837601,"lon":-103.095001,"elev":3297,"runways":[{"id":"03/21","lengthFt":5998,"widthFt":100,"surfaceCode":"CON","lowEnd":{"id":"03","heading":35,"lat":42.833,"lon":-103.099998,"displacedThresholdFt":290},"highEnd":{"id":"21","heading":215,"lat":42.8465,"lon":-103.086998,"displacedThresholdFt":500}},{"id":"12/30","lengthFt":4400,"widthFt":75,"surfaceCode":"CON","lowEnd":{"id":"12","heading":125,"lat":42.8381,"lon":-103.103996,"displacedThresholdFt":0},"highEnd":{"id":"30","heading":305,"lat":42.8312,"lon":-103.091003,"displacedThresholdFt":0}}]}
