{"key":"KCKP","icao":"KCKP","name":"Cherokee County Regional Airport","city":"Cherokee","state":"IA","lat":42.7317009,"lon":-95.55590057,"elev":1227,"runways":[{"id":"01/19","lengthFt":1941,"widthFt":120,"surfaceCode":"GRS","lowEnd":{"id":"01","heading":11,"lat":42.73070145,"lon":-95.55719757,"displacedThresholdFt":0},"highEnd":{"id":"19","heading":191,"lat":42.73609924,"lon":-95.55580139,"displacedThresholdFt":0}},{"id":"18/36","lengthFt":4001,"widthFt":75,"surfaceCode":"CON","lowEnd":{"id":"18","heading":183,"lat":42.73630142,"lon":-95.55529785,"displacedThresholdFt":200},"highEnd":{"id":"36","heading":3,"lat":42.72539902,"lon":-95.55599976,"displacedThresholdFt":0}}]}
