{"key":"KGSH","icao":"KGSH","name":"Goshen Municipal Airport","city":"Goshen","state":"IN","lat":41.526401519800004,"lon":-85.79290008539999,"elev":827,"runways":[{"id":"05/23","lengthFt":2267,"widthFt":175,"surfaceCode":"GRS","lowEnd":{"id":"05","heading":44.3,"lat":41.52590179,"lon":-85.79679871,"displacedThresholdFt":0},"highEnd":{"id":"23","heading":224.3,"lat":41.53099823,"lon":-85.79019928,"displacedThresholdFt":0}},{"id":"09/27","lengthFt":6008,"widthFt":100,"surfaceCode":"ASP","lowEnd":{"id":"09","heading":89.3,"lat":41.52529907,"lon":-85.80169678,"displacedThresholdFt":0},"highEnd":{"id":"27","heading":269.3,"lat":41.52539825,"lon":-85.78340149,"displacedThresholdFt":0}}]}
