{"key":"KGVL","icao":"KGVL","name":"Lee Gilmer Memorial Airport","city":"Gainesville","state":"GA","lat":34.27259827,"lon":-83.8302002,"elev":1276,"runways":[{"id":"05/23","lengthFt":5496,"widthFt":100,"surfaceCode":"ASP","lowEnd":{"id":"05","heading":41,"lat":34.26710129,"lon":-83.83789825,"displacedThresholdFt":0},"highEnd":{"id":"23","heading":221,"lat":34.2784996,"lon":-83.8259964,"displacedThresholdFt":0}},{"id":"11/29","lengthFt":4003,"widthFt":100,"surfaceCode":"ASP","lowEnd":{"id":"11","heading":108,"lat":34.27410126,"lon":-83.834198,"displacedThresholdFt":0},"highEnd":{"id":"29","heading":288,"lat":34.27080154,"lon":-83.82150269,"displacedThresholdFt":0}}]}
