{"key":"KHLG","icao":"KHLG","name":"Wheeling Ohio County Airport","city":"Wheeling","state":"WV","lat":40.1749992371,"lon":-80.6463012695,"elev":1195,"runways":[{"id":"03/21","lengthFt":5002,"widthFt":150,"surfaceCode":"ASP","lowEnd":{"id":"03","heading":26,"lat":40.16859818,"lon":-80.65129852,"displacedThresholdFt":0},"highEnd":{"id":"21","heading":206,"lat":40.18090057,"lon":-80.64350128,"displacedThresholdFt":0}},{"id":"16/34","lengthFt":4499,"widthFt":150,"surfaceCode":"ASP","lowEnd":{"id":"16","heading":151,"lat":40.18069839477539,"lon":-80.6489028930664,"displacedThresholdFt":0},"highEnd":{"id":"34","heading":331,"lat":40.169898986816406,"lon":-80.64109802246094,"displacedThresholdFt":0}}]}
