{"key":"KLVM","icao":"KLVM","name":"Mission Field","city":"Livingston","state":"MT","lat":45.6994018555,"lon":-110.447998047,"elev":4660,"runways":[{"id":"04/22","lengthFt":5701,"widthFt":75,"surfaceCode":"ASP","lowEnd":{"id":"04","heading":54.7,"lat":45.69329833984375,"lon":-110.45500183105469,"displacedThresholdFt":0},"highEnd":{"id":"22","heading":234.7,"lat":45.70240020751953,"lon":-110.43699645996094,"displacedThresholdFt":0}},{"id":"08/26","lengthFt":3762,"widthFt":125,"surfaceCode":"GRS","lowEnd":{"id":"08","heading":95,"lat":45.70159912,"lon":-110.4570007,"displacedThresholdFt":0},"highEnd":{"id":"26","heading":275,"lat":45.70080185,"lon":-110.4420013,"displacedThresholdFt":0}},{"id":"13/31","lengthFt":2724,"widthFt":120,"surfaceCode":"GRS","lowEnd":{"id":"13","heading":148.3,"lat":45.70330048,"lon":-110.4540024,"displacedThresholdFt":0},"highEnd":{"id":"31","heading":328.3,"lat":45.69689941,"lon":-110.4489975,"displacedThresholdFt":0}}]}
