{"key":"KSER","icao":"KSER","name":"Freeman Municipal Airport","city":"Seymour","state":"IN","lat":38.923599243164,"lon":-85.907402038574,"elev":583,"runways":[{"id":"05/23","lengthFt":6001,"widthFt":100,"surfaceCode":"ASP","lowEnd":{"id":"05","heading":44,"lat":38.91820145,"lon":-85.90740204,"displacedThresholdFt":0},"highEnd":{"id":"23","heading":224,"lat":38.92900085,"lon":-85.89399719,"displacedThresholdFt":0}},{"id":"09U/27U","lengthFt":1104,"widthFt":100,"surfaceCode":"TUR","lowEnd":{"id":"09U","heading":90,"lat":38.9314003,"lon":-85.91419983,"displacedThresholdFt":0},"highEnd":{"id":"27U","heading":270,"lat":38.9314003,"lon":-85.91059875,"displacedThresholdFt":0}},{"id":"14/32","lengthFt":5502,"widthFt":100,"surfaceCode":"ASP","lowEnd":{"id":"14","heading":134,"lat":38.9286994934082,"lon":-85.9209976196289,"displacedThresholdFt":0},"highEnd":{"id":"32","heading":314,"lat":38.9182014465332,"lon":-85.90709686279297,"displacedThresholdFt":0}},{"id":"18U/36U","lengthFt":1215,"widthFt":100,"surfaceCode":"TUR","lowEnd":{"id":"18U","heading":180,"lat":38.9314003,"lon":-85.91400146,"displacedThresholdFt":0},"highEnd":{"id":"36U","heading":0,"lat":38.92810059,"lon":-85.91400146,"displacedThresholdFt":0}}]}
