{"key":"KSNK","icao":"KSNK","name":"Winston Field","city":"Snyder","state":"TX","lat":32.690212,"lon":-100.948918,"elev":2430,"runways":[{"id":"08/26","lengthFt":4200,"widthFt":75,"surfaceCode":"ASP","lowEnd":{"id":"08","heading":90,"lat":32.69029998779297,"lon":-100.95899963378906,"displacedThresholdFt":0},"highEnd":{"id":"26","heading":270,"lat":32.69029998779297,"lon":-100.94599914550781,"displacedThresholdFt":0}},{"id":"17/35","lengthFt":5599,"widthFt":100,"surfaceCode":"ASP","lowEnd":{"id":"17","heading":180,"lat":32.70339966,"lon":-100.9489975,"displacedThresholdFt":0},"highEnd":{"id":"35","heading":360,"lat":32.68799973,"lon":-100.9489975,"displacedThresholdFt":0}}]}
