{"key":"KWLW","icao":"KWLW","name":"Willows Glenn County Airport","city":"Willows","state":"CA","lat":39.51639938,"lon":-122.2180023,"elev":141,"runways":[{"id":"13/31","lengthFt":3788,"widthFt":60,"surfaceCode":"ASP","lowEnd":{"id":"13","heading":145.2,"lat":39.52119827,"lon":-122.2200012,"displacedThresholdFt":0},"highEnd":{"id":"31","heading":325.2,"lat":39.51169968,"lon":-122.2109985,"displacedThresholdFt":0}},{"id":"16/34","lengthFt":4125,"widthFt":100,"surfaceCode":"ASP","lowEnd":{"id":"16","heading":178.2,"lat":39.52270126,"lon":-122.2200012,"displacedThresholdFt":0},"highEnd":{"id":"34","heading":358.2,"lat":39.51029968,"lon":-122.2190018,"displacedThresholdFt":0}}]}
